README.md
setup.py
cmd_monitor/__init__.py
cmd_monitor/cmd_monitor.py
cmd_monitor.egg-info/PKG-INFO
cmd_monitor.egg-info/SOURCES.txt
cmd_monitor.egg-info/dependency_links.txt
cmd_monitor.egg-info/entry_points.txt
cmd_monitor.egg-info/top_level.txt