Metadata-Version: 1.1
Name: cmd-monitor
Version: 0.1
Summary: python plugin for vim debugger
Home-page: https://github.com/esquires/cmd_monitor
Author: Eric Squires
Author-email: eric.g.squires@gmail.com
License: GPL
Platform: UNKNOWN
Classifier: Development Status :: 4 - Beta
Classifier: Intended Audience :: Developers
Classifier: License :: OSI Approved :: MIT License
Classifier: Operating System :: Unix
Classifier: Operating System :: POSIX :: Linux
